foxpath/__init__.py
foxpath/foxpath.py
foxpath/utils.py
foxpath-2.0.2.dist-info/DESCRIPTION.rst
foxpath-2.0.2.dist-info/METADATA
foxpath-2.0.2.dist-info/RECORD
foxpath-2.0.2.dist-info/WHEEL
foxpath-2.0.2.dist-info/metadata.json
foxpath-2.0.2.dist-info/top_level.txt
tests/__init__.py
tests/check_file_tests.py
tests/step_definitions.py
tests/test_files.py
tests/test_list.py
tests/test_simple.py
