Metadata-Version: 2.0
Name: foxpath
Version: 2.0.2
Summary: Python library for running FoXPath tests against XML
Home-page: UNKNOWN
Author: Andy Lulham
Author-email: andy.lulham@publishwhatyoufund.org
License: MIT
Platform: UNKNOWN
Requires-Dist: lxml (==4.1.0)
Requires-Dist: PyYAML (==3.12)
Requires-Dist: six (==1.11.0)
Requires-Dist: gherkin-official (==4.1.3)
